MANIFEST.in
README.md
setup.py
pyoptica/__init__.py
pyoptica/distribution.py
pyoptica/holography.py
pyoptica/image.py
pyoptica/imaging_system.py
pyoptica/logging.py
pyoptica/plotting.py
pyoptica/run.py
pyoptica/utils.py
pyoptica/wavefront.py
pyoptica/zernikes.py
pyoptica.egg-info/PKG-INFO
pyoptica.egg-info/SOURCES.txt
pyoptica.egg-info/dependency_links.txt
pyoptica.egg-info/not-zip-safe
pyoptica.egg-info/requires.txt
pyoptica.egg-info/top_level.txt
pyoptica/optical_elements/__init__.py
pyoptica/optical_elements/base_optical_element.py
pyoptica/optical_elements/binary_grating.py
pyoptica/optical_elements/circular_reticle.py
pyoptica/optical_elements/diffuser.py
pyoptica/optical_elements/free_space.py
pyoptica/optical_elements/rectangular_reticle.py
pyoptica/optical_elements/siemens_star.py
pyoptica/optical_elements/thin_lens.py