Metadata-Version: 2.1
Name: pyoptica
Version: 0.6.2
Summary: Tools to apply light propagation algorithms
Home-page: https://gitlab.com/pyoptica
Author: Maciej Grochowicz, Michal Miler
Author-email: pyoptica@protonmail.com
License: MIT License
Keywords: fourier_optics light_propagation
Platform: UNKNOWN
Classifier: Programming Language :: Python :: 3.7
Classifier: Intended Audience :: Science/Research
Classifier: Topic :: Scientific/Engineering :: Mathematics
